soundbook/__init__.py
soundbook/soundbook.py
soundbook/core/__init__.py
soundbook/core/handler.py
soundbook/core/runner.py
soundbook/modules/__init__.py
soundbook/modules/add_cover_image.py
soundbook/modules/extract_audio.py
soundbook/modules/get_book.py
soundbook/modules/get_cover_image.py
soundbook/modules/get_title.py
soundbook/modules/get_url.py
soundbook/modules/make_folder.py
soundbook/modules/merge_audio.py
soundbook-0.0.4.dist-info/LICENSE
soundbook-0.0.4.dist-info/METADATA
soundbook-0.0.4.dist-info/WHEEL
soundbook-0.0.4.dist-info/entry_points.txt
soundbook-0.0.4.dist-info/top_level.txt
soundbook-0.0.4.dist-info/RECORD
