Metadata-Version: 2.1
Name: soundbook
Version: 0.0.4
Summary: easily download and merge split online audiobooks
Home-page: https://github.com/erfansamandarian/soundbook
Author: Erfan Samandarian
Author-email: mail@erfansamandarian.com
License: MIT
License-File: LICENSE
Requires-Dist: setuptools
Requires-Dist: ffmpeg
Requires-Dist: mutagen
Requires-Dist: eyed3
Requires-Dist: pillow
Requires-Dist: requests
Requires-Dist: sox
Requires-Dist: yt-dlp
